pyarabicshaping/__init__.py
pyarabicshaping/arabicshapingtab.py
pyarabicshaping/joiningtypetab.py
pyarabicshaping/pyarabicshaping.py
pyarabicshaping-1.0.dist-info/LICENSE.md
pyarabicshaping-1.0.dist-info/METADATA
pyarabicshaping-1.0.dist-info/WHEEL
pyarabicshaping-1.0.dist-info/top_level.txt
pyarabicshaping-1.0.dist-info/RECORD
