Metadata-Version: 2.1
Name: pyarabicshaping
Version: 1.0
Summary: arabic shapes
Home-page: https://github.com/vorujack/pyarabicshaping
Author: vorujack
Author-email: vorujack@gmail.com
License: MIT
Download-URL: https://github.com/vorujack/pyarabicshaping/tarball/1.0
Keywords: arabic
Platform: UNKNOWN
